odoo/addons/shopfloor_checkout_package_measurement/README.rst
odoo/addons/shopfloor_checkout_package_measurement/__init__.py
odoo/addons/shopfloor_checkout_package_measurement/__manifest__.py
odoo/addons/shopfloor_checkout_package_measurement/actions/__init__.py
odoo/addons/shopfloor_checkout_package_measurement/actions/data.py
odoo/addons/shopfloor_checkout_package_measurement/actions/message.py
odoo/addons/shopfloor_checkout_package_measurement/actions/schema.py
odoo/addons/shopfloor_checkout_package_measurement/i18n/fr_BE.po
odoo/addons/shopfloor_checkout_package_measurement/i18n/it.po
odoo/addons/shopfloor_checkout_package_measurement/i18n/shopfloor_checkout_package_measurement.pot
odoo/addons/shopfloor_checkout_package_measurement/readme/CONTRIBUTORS.rst
odoo/addons/shopfloor_checkout_package_measurement/readme/DESCRIPTION.rst
odoo/addons/shopfloor_checkout_package_measurement/services/__init__.py
odoo/addons/shopfloor_checkout_package_measurement/services/checkout.py
odoo/addons/shopfloor_checkout_package_measurement/static/description/icon.png
odoo/addons/shopfloor_checkout_package_measurement/static/description/index.html
odoo/addons/shopfloor_checkout_package_measurement/tests/__init__.py
odoo/addons/shopfloor_checkout_package_measurement/tests/test_checkout_package_measurement.py
odoo14_addon_shopfloor_checkout_package_measurement-14.0.1.2.0.dist-info/METADATA
odoo14_addon_shopfloor_checkout_package_measurement-14.0.1.2.0.dist-info/WHEEL
odoo14_addon_shopfloor_checkout_package_measurement-14.0.1.2.0.dist-info/top_level.txt
odoo14_addon_shopfloor_checkout_package_measurement-14.0.1.2.0.dist-info/RECORD
